findit_client
