Metadata-Version: 1.0
Name: findit-client
Version: 0.1.6
Summary: client for findit, with no opencv needed
Home-page: https://github.com/williamfzc/findit_client
Author: williamfzc
Author-email: fengzc@vip.qq.com
License: UNKNOWN
Platform: UNKNOWN
